counter/__init__.py
counter/__main__.py
counter/builder.py
counter/converter.py
counter/writer.py
counter/static/css/auto-complete.css
counter/static/css/mui.css
counter/static/css/style.css
counter/static/data/menu.csv
counter/static/img/delete.png
counter/static/img/favicon.png
counter/static/img/le_bigmac.png
counter/static/img/page.png
counter/static/js/auto-complete.js
counter/static/js/food.js
counter/static/js/food.json
counter/static/js/handler.js
counter/static/js/mui.js
counter/templates/index.html
counter/view/__init__.py
counter/view/home.py
tests/__init__.py
tests/test_builder.py
tests/test_converter.py
calorie_counter-0.1.3.dist-info/LICENSE.md
calorie_counter-0.1.3.dist-info/METADATA
calorie_counter-0.1.3.dist-info/WHEEL
calorie_counter-0.1.3.dist-info/top_level.txt
calorie_counter-0.1.3.dist-info/RECORD
