Metadata-Version: 2.1
Name: calorie-counter
Version: 0.1.3
Summary: This project represents simple web app to calculate calories based on given food type.
Home-page: https://github.com/vyahello/calorie-counter
Author: Volodymyr Yahello
Author-email: vyahello@gmail.com
License: UNKNOWN
Platform: UNKNOWN
Classifier: Programming Language :: Python :: 3.6
Classifier: Programming Language :: Python :: 3.7
Classifier: Programming Language :: Python :: 3.8
Classifier: License :: OSI Approved :: MIT License
Classifier: Operating System :: OS Independent
Requires-Python: >=3.6
Requires-Dist: flask (==1.1.1)
Requires-Dist: python-dotenv (==0.10.3)
Requires-Dist: gunicorn (==20.0.0)
Requires-Dist: setuptools (==42.0.2)
Requires-Dist: wheel (==0.33.6)
Requires-Dist: twine (==3.1.1)
Requires-Dist: click (==7.0.0)
